async_llms/__init__.py
async_llms/cli.py
async_llms/inference.py
async_llms/llms/__init__.py
async_llms/llms/google_llm.py
async_llms/llms/openai_llm.py
async_llms/llms/together_llm.py
async_llms/llms/xai_llm.py
async_llms-0.3.7.dist-info/licenses/LICENSE
async_llms-0.3.7.dist-info/METADATA
async_llms-0.3.7.dist-info/WHEEL
async_llms-0.3.7.dist-info/entry_points.txt
async_llms-0.3.7.dist-info/top_level.txt
async_llms-0.3.7.dist-info/RECORD
