Metadata-Version: 2.4
Name: async-llms
Version: 0.3.7
Summary: A Python library for making asynchronous LLM calls
Author-email: "Cheng-Kuang (Brian) Wu" <brianckwu@gmail.com>
License-Expression: MIT
Project-URL: Homepage, https://github.com/Brian-Ckwu/async-llms
Classifier: Programming Language :: Python :: 3
Classifier: Operating System :: OS Independent
Requires-Python: >=3.10
License-File: LICENSE
Requires-Dist: tqdm
Requires-Dist: aiohttp
Requires-Dist: openai
Requires-Dist: aiofiles
Requires-Dist: google
Dynamic: license-file
